{
  "УВЕРЕННОСТЬ_В_ЗАВТРА": {
    "patterns": ["уверенн", "стабильн", "не бояться", "спокойств", "надёжн", "надежн", "гарантир", "подушк.*безопасн"],
    "job": "Хочу чувствовать уверенность в завтрашнем дне"
  },
  "НЕЗАВИСИМОСТЬ": {
    "patterns": ["независим", "свобод", "сам.*решаю", "не зависеть", "на себя", "без.*начальник", "без.*работодател"],
    "job": "Хочу не зависеть от начальника / государства / мужа"
  },
  "ГОРДОСТЬ_ЗА_РЕЗУЛЬТАТ": {
    "patterns": ["гордиться", "горжусь", "достижени", "результат.*свой", "сделал.*сам", "мой.*продукт", "моё.*приложени"],
    "job": "Хочу гордиться тем, что создал своими руками"
  },
  "СТРАХ_БЕДНОСТИ": {
    "patterns": ["не хватает", "экономлю", "считаю.*копейк", "нищет", "бедн", "долг", "кредит", "рассрочк"],
    "job": "Боюсь бедности и финансовой зависимости"
  },
  "НАДЕЖДА_НА_ПЕРЕМЕНЫ": {
    "patterns": ["наконец", "давно.*хотел", "пора", "решился", "это.*шанс", "последн.*попытк", "не упустить"],
    "job": "Чувствую что это мой шанс изменить жизнь"
  }
}
